PyAngle/Angle.py
PyAngle/AngleTest.py
PyAngle/__init__.py
PyAngle/__version__.py
PyAngle-1.0.0.dist-info/DESCRIPTION.rst
PyAngle-1.0.0.dist-info/METADATA
PyAngle-1.0.0.dist-info/RECORD
PyAngle-1.0.0.dist-info/WHEEL
PyAngle-1.0.0.dist-info/metadata.json
PyAngle-1.0.0.dist-info/top_level.txt
