Metadata-Version: 2.0
Name: PyAngle
Version: 1.0.0
Summary: A Simple Package For Angle Calculation
Home-page: https://github.com/gzn00417/PyAngle
Author: Guo Zhuoning
Author-email: gzn00417@foxmail.com
License: MIT
Platform: UNKNOWN
Classifier: License :: OSI Approved :: MIT License
Classifier: Programming Language :: Python
Classifier: Programming Language :: Python :: 3
Classifier: Programming Language :: Python :: 3.6
Classifier: Programming Language :: Python :: Implementation :: CPython
Classifier: Programming Language :: Python :: Implementation :: PyPy
Requires-Python: >=3.6.0
